{
    "title": "遵义市汇川区",
    "category": [
        {
            "id": "7",
            "category": "中国地名"
        },
        {
            "id": "35",
            "category": "贵州省"
        },
        {
            "id": "850",
            "category": "遵义市"
        }
    ],
    "detail": "[日期：2014-04-09]   来源：www.Youlai19.cn  作者：【由来网】   阅读：432次",
    "content": [
        {
            "type": "text",
            "text": "【由来】\r\n       2003年由红花岗区和遵义县北部划出部分地区，在原遵义经济技术开发区的基础上，新成立汇川区。因区政府所在地地名为汇川坝，故冠名为汇川区。"
        },
        {
            "type": "text",
            "text": "【沿革】\r\n       1992年7月，经贵州省人民政府批准，成立了遵义经济技术开发区，规划面积为14平方公里，1998年遵义经济技术开发区党工委、管委会调整为中共遵义市委、市人民政府的正县级派出机构。2003年12月26日，国务院批复同意，成为贵州省第88个县级行政区，因区政府所在地地名为汇川坝，且查阅全国其他县、市、区、镇、街无此名，故冠名为汇川区。"
        },
        {
            "type": "text",
            "text": "       [ 参看“遵义县”词条]"
        },
        {
            "type": "text",
            "text": "       [ 参看“遵义市红花岗区”词条]"
        }
    ]
}