{
    "title": "梧州市蝶山区",
    "category": [
        {
            "id": "7",
            "category": "中国地名"
        },
        {
            "id": "33",
            "category": "广西壮族自治区"
        },
        {
            "id": "939",
            "category": "梧州市"
        }
    ],
    "detail": "[日期：2014-04-20]   来源：www.Youlai19.cn  作者：【由来网】   阅读：429次",
    "content": [
        {
            "type": "text",
            "text": "【由来】\r\n       1958年置河西区，1962年改蝶山区，以区内蝴蝶山得名。"
        },
        {
            "type": "text",
            "text": "【沿革】\r\n       秦始皇南取百越，置南海、桂林、象郡三郡，区地属桂林郡。汉初赵佗并桂林郡、象郡称南越国，并封其宗弟赵光为苍梧王，治广信，本区地属广信。汉元鼎六年（前111年），苍梧王赵光降汉后，始设苍梧郡，治所在苍梧王城，今梧州属交趾刺史部苍梧郡广信县。"
        },
        {
            "type": "text",
            "text": "       隋开皇三年（583年）更广信县为苍梧县，今蝶山区属苍梧县。唐武德四年（621年）置梧州，区地属梧州。明代，梧州府与苍梧县府县同驻城区。苍梧县城划为华岳、善教、富德、宝伦、阜民等5厢，淳政、通泰、迎恩、水西、育真等5坊。水西访即今蝶山区区域内。清代沿用明制，全县划为11坊1所11乡。其中水西坊及富民坊均在今蝶山区范围之内。"
        },
        {
            "type": "text",
            "text": "       民国十六年（1927年），成立梧州市政府，为省辖市，以原苍梧县城区（今万秀区辖境），三角嘴（今蝶山区辖境）及西江南岸火山至高旺一带为在政区域。民国二十一年（1932年），撤市复归苍梧县、治梧州。民国二十二年（1933年），全县分梧州、戎城等7个区，梧州区辖8镇7乡，其中河滨镇、富民乡、龙华乡大塘村一带为今蝶山区属地。民国三十六年（1947年），撤销区建制，梧州城内分为城东、城南、城中、城北、河滨等5镇和鸳江乡。"
        },
        {
            "type": "text",
            "text": "       1949年11月25日梧州解放。1950年1月，在蝶山区辖境内，设立河滨镇公所。1953年5月，撤销河滨镇公所，其所管辖的地段范围划归第二区人民政府。1955年8月，撤销第二区人民政府，所辖的大部分地段划为角嘴街道办事处。1958年9月，角嘴街道办事处改称河西区公所。1960年4月，撤销河西区公所，成立蝶山人民公社。1961年11月，在蝶山人民公社的基础上成立区公所（1962年8月前称河西区公所，之后称蝶山区公所）。1962年8月，实行政社合一。"
        },
        {
            "type": "text",
            "text": "       1968年9月，蝶山人民公社改称梧州市向阳人民公社革命委员会。1979年2月，城区人民公社改建为市辖区，向阳人民公社革命委员会改称梧州市蝶山区革命委员会。1980年8月，蝶山区召开第三届人民代表大会，选举产生了蝶山区人民政府。"
        }
    ]
}