{
    "title": "澳门",
    "category": [
        {
            "id": "7",
            "category": "中国地名"
        },
        {
            "id": "30",
            "category": "澳门特区"
        }
    ],
    "detail": "[日期：2014-05-14]   来源：www.Youlai19.cn  作者：【由来网】   阅读：538次",
    "content": [
        {
            "type": "text",
            "text": "【由来】\r\n       澳门以前是个小渔村，它的本名为濠镜或濠镜澳，因为当时泊口可称为“澳”。"
        },
        {
            "type": "text",
            "text": "       澳门及其附近盛产蚝（即牡蛎），蚝壳内壁光亮如镜，澳门因此被称为蚝镜。后人把这个名称改为较文雅的“濠镜”。清乾隆年间出版的《澳门纪略》中说：“濠镜之名，着于《明史》。东西五六里、南北半之，有南北二湾，可以泊船。或曰南北二湾，规圆如镜，故曰濠镜。”从这个名称中，又引申出濠江、海镜、镜海等一连串澳门的别名"
        },
        {
            "type": "text",
            "text": "【传说】\r\n       澳门这个名字则源于渔民非常敬仰的一位中国女神──天后，她又名娘妈。据说，一艘渔船在天气晴朗、风平浪静的日子里航行，突遇狂风雷暴，渔民处于危难。危急关头，一位少女站了出来，下令风暴停止。风竟然止住了，大海也恢复了平静，渔船平安地到达了海镜港。上岸后，少女朝妈阁山走去，忽然一轮光环照耀，少女化做一缕青烟。后来，人们在她登岸的地方，建了一座庙宇供奉这位娘妈。"
        },
        {
            "type": "text",
            "text": "【附加】\r\n       十六世纪中叶，第一批葡萄牙人抵澳时，询问居民当地的名称，居民误以为指庙宇，答称“妈阁”。葡萄牙人以其音而译成“MACAU”，成为澳门葡文名称的由来。"
        }
    ]
}