{
    "title": "吉水县",
    "category": [
        {
            "id": "7",
            "category": "中国地名"
        },
        {
            "id": "27",
            "category": "江西省"
        },
        {
            "id": "1206",
            "category": "吉安市"
        },
        {
            "id": "1253",
            "category": "吉水县"
        }
    ],
    "detail": "[日期：2014-06-12]   来源：www.Youlai19.cn  作者：【由来网】   阅读：1175次",
    "content": [
        {
            "type": "text",
            "text": "【由来】\r\n       南唐保大八年（950年），析庐陵县水东11乡置吉水县，因境内吉水（也称吉永水）得名。"
        },
        {
            "type": "text",
            "text": "       赣江和恩江在县境交汇，中有沙洲，状若“吉”字。另据《太平寰宇记》：“吉永水在县东北十里，源出永安乡，北会于赣水。”"
        },
        {
            "type": "text",
            "text": "【沿革】\r\n       夏、商时代，地域处扬州西境。周朝，地属吴、越、楚。"
        },
        {
            "type": "text",
            "text": "       秦朝，地属九江郡庐陵县。西汉，地属豫章郡庐陵县、新干县。新朝，地属九江郡桓亭县。东汉，建武元年（25年），桓亭县复名庐陵。初平二年（191年），分豫章立庐陵郡，县名石阳，复析置吉阳县，皆属庐陵郡。"
        },
        {
            "type": "text",
            "text": "       三国，地属吴国庐陵郡石阳县、吉阳县。晋朝，太康元年（280年），司马炎平吴，庐陵郡治迁石阳，县属沿旧。咸康八年（342年），庐陵太守孔伦移庐陵治于今吉安市区，石阳县治随徙。"
        },
        {
            "type": "text",
            "text": "       南朝，梁天监元年（502年），武帝灭齐，高昌县（今吉安县）并入石阳县，隶属庐陵郡，郡县同治所。"
        },
        {
            "type": "text",
            "text": "       隋朝，开皇十年（590年），改庐陵郡为吉州，改石阳县为庐陵县。次年，撤销吉阳（今吉水）、兴平（今永丰）、阳丰（今永丰）三县，并入庐陵县，隶属吉州。大业三年（607年）。改吉州为庐陵郡，庐陵县隶属不变。"
        },
        {
            "type": "text",
            "text": "       唐朝，武德五年（622年），复置吉州，庐陵仍为附廓县。开元二十一年（733年），江南道分东、西二道，庐陵县属江南西道吉州。天宝元年（742年），改吉州庐陵郡为吉州，县属不变。"
        },
        {
            "type": "text",
            "text": "       五代十国，吴天祐六年（909年），庐陵县属杨吴领地。南唐保大八年（950年），析庐陵水东11乡置吉水县，此为吉水县名之始，盖赣江和恩江在县境交汇，中有沙洲，状若“吉”字。"
        },
        {
            "type": "text",
            "text": "       北宋，雍熙元年（984年），析庐陵地置县，仍名吉水。宋至和二年（1055年），析吉水县置永丰县，以永丰乡得名，皆属吉州。南宋，吉水县，属吉州。"
        },
        {
            "type": "text",
            "text": "       元朝，元贞元年（1295年）升州，属吉安路。明朝，复降为县，属吉安府。清朝，吉水县，属吉安府。"
        },
        {
            "type": "text",
            "text": "       民国元年（1912年）废府撤道，吉水县直属于省。民国三年（1914年）吉水县属庐陵道。民国十五年（1926年），废道，吉水县直属江西省。民国二十一年（1932年），属第九行政区。民国二十四年（1935年），属第三行政区。"
        },
        {
            "type": "text",
            "text": "       民国三十八年（1949年）7月吉水县解放，属吉安分区。1949年9月，吉安分区改为吉安专区。1968年5月，吉安专区改名井冈山地区，吉水县属井冈山地区。1979年7月改井冈山地区为吉安地区，吉水县属吉安地区。2000年5月11日，撤销吉安地区，成立地级吉安市，吉水县隶属吉安市。同时，富滩镇划归地级吉安市青原区。"
        }
    ]
}