{
    "title": "鹰潭市月湖区",
    "category": [
        {
            "id": "7",
            "category": "中国地名"
        },
        {
            "id": "27",
            "category": "江西省"
        },
        {
            "id": "1204",
            "category": "鹰潭市"
        }
    ],
    "detail": "[日期：2014-07-02]   来源：www.Youlai19.cn  作者：【由来网】   阅读：1253次",
    "content": [
        {
            "type": "text",
            "text": "【由来】\r\n       1983年鹰潭市区改名为月湖区，因境内西南有一奇岩，“岩洞半月形，洞临白露河，河宽似湖”而得名。"
        },
        {
            "type": "text",
            "text": "【沿革】\r\n       秦始皇二十四年（前223年），至唐广德二年（764年），鹰潭属余干县晋兴乡辖地。唐永泰元年（765年），置贵溪县，鹰潭称坊，为贵溪县辖地。"
        },
        {
            "type": "text",
            "text": "       明万历初年（1573年），神峰寨巡检司迁鹰潭。清代鹰潭镇为仙源乡三十一都、八图。"
        },
        {
            "type": "text",
            "text": "       清乾隆三十年（1765年），鹰潭设司。同治三年（1864年），鹰潭司改鹰潭镇，仍为贵溪县管辖。"
        },
        {
            "type": "text",
            "text": "       民国十年（1921年），始有月湖乡建置，时辖12保、94甲。民国二十年（1931年），鹰潭为第四区，设一保联，辖17保。民国二十九年（1940年）八月，鹰潭第四区已成为经济轴心，为此，增设月湖乡。民国三十八年（1949年）5月，鹰潭解放，鹰潭镇改为区。同年9月，废保甲，实行区、乡、村制。"
        },
        {
            "type": "text",
            "text": "       1950年6月，鹰潭镇为区级镇。8月，增设月湖区（第5区）。1951年，月湖区在管辖13个乡的基础上又增设西汪、下桂、天禄。1957年1月1日，鹰潭镇升格为上饶专区直辖镇，划贵溪县嘴上，白露港、杨碧3个乡归鹰潭镇。2月又将贵溪县低坪乡划入鹰潭镇。"
        },
        {
            "type": "text",
            "text": "       1960年，鹰潭镇再次为上饶专区直辖镇。1979年3月，鹰潭撤镇设市。1983年7月，鹰潭升为省辖市，原市区改为县级月湖区。"
        }
    ]
}