{
    "title": "醴陵市",
    "category": [
        {
            "id": "7",
            "category": "中国地名"
        },
        {
            "id": "25",
            "category": "湖南省"
        },
        {
            "id": "1370",
            "category": "株洲市"
        },
        {
            "id": "1462",
            "category": "醴陵市"
        }
    ],
    "detail": "[日期：2014-08-08]   来源：www.Youlai19.cn  作者：【由来网】   阅读：826次",
    "content": [
        {
            "type": "text",
            "text": "【由来】\r\n       据《古今图书集成》：东汉析湖南地置醴陵。名称源于县北三里姜村一甘泉，泉水略有淡酒味，故名醴泉。据《名胜志》曰：县北有陵，陵下有井，涌泉如醴，因以名县。据《史记》：“汉高后四年，封越以醴陵国为食邑。”东汉初，析临湘县置醴陵县，乃以故国名县。"
        },
        {
            "type": "text",
            "text": "【沿革】\r\n       古属荆州之域，春秋、战国属楚。西汉为临湘县地，高后四年（前184年）封长沙王刘越为醴陵侯，“醴陵”之名自此始。东汉初，析临湘县置醴陵县，属长沙郡。三国时，醴陵属吴国荆州长沙郡。南北朝宋属湘州长沙内史；齐以后属湘州长沙郡。"
        },
        {
            "type": "text",
            "text": "       隋初属荆州长沙郡；大业三年（607年），改临湘县为长沙县，撤醴陵县建置，以其地并入长沙县。唐武德四年（621年），分长沙县地复置醴陵县，属江南西道潭州长沙郡。五代十国时，属楚国潭州长沙府。"
        },
        {
            "type": "text",
            "text": "       元朝元贞元年（1295年）升为醴陵州，属湖广行省岭北湖南道天临路。明洪武二年（1369年）复降为县，隶湖广布政使司长沙府。清朝沿袭明制，康熙三年（1664年），湖南建省后，醴陵县属湖南省长宝道长沙府。"
        },
        {
            "type": "text",
            "text": "       民国元年（1912年），废长沙府，醴陵县直属于省。民国三年（1914年）5月置湘江道，醴陵县属湘江道。民国九年（1920年）。废道，醴陵县直属于省。民国二十六年（1937年）设立第一行政督察区，辖有岳阳县、长沙县、湘阴县、临湘县、浏阳县、平江县、湘潭县、醴陵县、益阳县和宁乡县计10县，专署驻浏阳县。抗战后一度废除本区，改由省府管辖，民国三十六年（1947年）以后恢复本区。"
        },
        {
            "type": "text",
            "text": "       民国三十八年（1949年）7月25日，醴陵县解放，属长沙专区。1952年，长沙专区改名湘潭专区，湘潭县隶湘潭专区。1968年9月，湘潭专区改称湘潭地区，醴陵县属湘潭地区。1983年7 月，醴陵县改属株洲市。1985年5月24日，撤销醴陵县，设立醴陵市（县级），8月15日挂牌成立。"
        }
    ]
}