{
    "title": "株洲市天元区",
    "category": [
        {
            "id": "7",
            "category": "中国地名"
        },
        {
            "id": "25",
            "category": "湖南省"
        },
        {
            "id": "1370",
            "category": "株洲市"
        }
    ],
    "detail": "[日期：2014-08-08]   来源：www.Youlai19.cn  作者：【由来网】   阅读：517次",
    "content": [
        {
            "type": "text",
            "text": "【由来】\r\n       1997年5月31日，株洲市设立天元区，因境内有天台山、园艺场，取“园”之谐音“元”，合名为天元。"
        },
        {
            "type": "text",
            "text": "【沿革】\r\n       解放初，辖区分属湘潭县藕花乡、藕灵乡。1959年划属株洲市郊区，1965年划归株洲县；1966年园艺场复划入株洲市郊区；"
        },
        {
            "type": "text",
            "text": "       1992年2月经湖南省人民政府批准，于园艺场辖区范围成立株洲高新技术产业开发区，同年12月经国务院批准为国家级开发区。1997年5月31日，设立天元区，辖原株洲县的群丰镇、马家河乡和原郊区的园艺场。\n\r\n       [参看“株洲市”词条]"
        }
    ]
}