{
    "title": "安吉县",
    "category": [
        {
            "id": "7",
            "category": "中国地名"
        },
        {
            "id": "24",
            "category": "浙江省"
        },
        {
            "id": "1474",
            "category": "湖州市"
        },
        {
            "id": "1513",
            "category": "安吉县"
        }
    ],
    "detail": "[日期：2014-08-17]   来源：www.Youlai19.cn  作者：【由来网】   阅读：556次",
    "content": [
        {
            "type": "text",
            "text": "【由来】\r\n       汉灵帝中平二年（185年），割故鄣县南境置安吉县，县治设于天目乡（今孝丰镇），取《诗经》：“安且吉兮”句，为安吉得名之始。"
        },
        {
            "type": "text",
            "text": "【沿革】\r\n       春秋时期，始筑故鄣城（今址安城镇古城村），曾一度作为越国首都，至秦代设鄣郡于此。汉武帝元狩二年（前121年），更设鄣郡为丹阳郡，迁治宛陵，并在鄣郡故地设故鄣县。"
        },
        {
            "type": "text",
            "text": "       东汉末期，因故鄣县辖境广袤辽阔（大致包括今安吉县全境、长兴县西南一部和安徽省广德县全境、郎溪县一部），为强化控制，朝廷于黄巾大起义的第二年，即灵帝中平二年（185），割故鄣县南境置安吉县，县治设于天目乡（今孝丰镇），故鄣、安吉两县均隶属丹阳郡。安吉建县始于此，至今已1800余年。"
        },
        {
            "type": "text",
            "text": "       三国吴宝鼎元年（公元266年），安吉属新设的吴兴郡。隋开皇九年（589年）废郡并县，安吉县被撤，并入绥安县。绥安初属宣州，仁寿二年（602年）又改属湖州。义宁二年（618年）复置安吉县，属吴兴郡。"
        },
        {
            "type": "text",
            "text": "       唐武德四年（621年），安吉改属桃州。武德七年，安吉县又被撤销，并入长城县（今长兴县），属湖州。唐麟德元年（664年），恢复安吉县建制，隶湖州。安吉县经过七十多年的撤而复设，从此稳定下来。唐开元二十六年（738），将县治北移至今安城镇址附近。"
        },
        {
            "type": "text",
            "text": "       宋元两代，南宋宝庆元年（1225年）改湖州为安吉州。"
        },
        {
            "type": "text",
            "text": "       元至元十三年（1276年）改安吉州为湖州路，安吉仍分属安吉州和湖州路。元至正十八年（公元1358年），安吉属长安州（后改为长兴州）。至正二十七年，又属湖州府。"
        },
        {
            "type": "text",
            "text": "       明宪宗成化二十三年（1487年）析安吉县分置孝丰县。明武宗正德元年（1506年）升安吉县为州，领孝丰县，隶湖州府。清高宗乾隆三十九年（1774年）安吉州复降为县，与孝丰县并入湖州府。"
        },
        {
            "type": "text",
            "text": "       民国元年（1912年），废府设道，安吉、孝丰两县同属钱塘道。民国十六年（1927年）道废，安吉县直属浙江省。民国二十四年（1935年）7月，省政府将全省划为9区，安吉县属第一行政督察区。民国二十九年（1940年）1月，为适应战时需要，省政府将9区调整为10个行政督察区，安吉县为第二行政督察区专署驻地。民国三十六年（1947年）3月，全省调整为6个行政督察区，安吉县属第一区。民国三十七年（1948年），省政府将6区调整为9个行政督察区，安吉县隶属第九区。\n\r\n       民国三十八年（1949年）4月30日，安吉县解放，5月1日，孝丰县解放，两县均隶属第九行政区。10月第九行政区改为临安专区。1953年初临安专区撤销，安吉县、孝丰县划归嘉兴专区。1958年10月孝丰县并入安吉县，仍属嘉兴专区。1973年嘉兴专区改称嘉兴地区，安吉县随属。1983年7月，撤销嘉兴地区，设立湖州市、嘉兴两地级市，安吉县隶属湖州市至今。"
        }
    ]
}