{
    "title": "温泉县",
    "category": [
        {
            "id": "7",
            "category": "中国地名"
        },
        {
            "id": "44",
            "category": "新疆维吾尔族自治区"
        },
        {
            "id": "133",
            "category": "博尔塔拉蒙古自治州"
        },
        {
            "id": "160",
            "category": "温泉县"
        }
    ],
    "detail": "[日期：2014-02-15]   来源：www.Youlai19.cn  作者：【由来网】   阅读：403次",
    "content": [
        {
            "type": "text",
            "text": "【由来】\r\n       1938年由博尔塔拉县（1950年改名为博乐县）析置温泉设治局，1941年改为温泉县。温泉，系蒙古语“阿日相”的意译，因县多温泉，故名。它的另外一个名字叫博格达尔，系蒙古语，意为“神山的背后”。"
        },
        {
            "type": "text",
            "text": "【沿革】\r\n       县境自古以来就是我国历史上的北方少数民族或部族的游牧地。春秋战国时期，为塞种人游牧地。秦汉时期，先后为月氏和乌孙人的游牧地。隋朝时属西突厥地。唐朝初叶，归双河都护府所辖，仍为西突厥人游牧地。唐朝中叶至宋朝末年，为葛罗禄人占据，隶属西辽。"
        },
        {
            "type": "text",
            "text": "       元朝为察合台王领地。明朝相继为哈萨克族、厄鲁特蒙古部族的游牧地。清朝清乾隆平定准噶尔叛乱后，派遣蒙古察哈尔部老八旗驻防在这一带。为伊犁将军所统辖的察哈尔蒙古营左翼屯田之地。清光绪十四年（1888年），设精河抚民直隶厅，简称精河厅，隶伊塔道。今温泉县为精河直隶厅辖境。"
        },
        {
            "type": "text",
            "text": "       1938年由博尔塔拉县（1950年改名为博乐县）析置温泉设治局于此，隶属伊犁行政区。1941年温泉设治局改为温泉县，隶属伊犁专区。"
        },
        {
            "type": "text",
            "text": "       1949年9月新疆和平解放后，温泉县属伊犁专署领导。1954年7月13日博尔塔拉蒙古族自治区成立，1955年2月自治区改称自治州，温泉县属博尔塔拉蒙古自治州。"
        }
    ]
}