{
    "title": "安庆市宜秀区",
    "category": [
        {
            "id": "7",
            "category": "中国地名"
        },
        {
            "id": "23",
            "category": "安徽省"
        },
        {
            "id": "1543",
            "category": "安庆市"
        }
    ],
    "detail": "[日期：2014-10-30]   来源：www.Youlai19.cn  作者：【由来网】   阅读：516次",
    "content": [
        {
            "type": "text",
            "text": "【由来】\r\n       2005年5月13日，安庆区划调整，撤销郊区，成立宜秀区。因为安庆别称为“宜城”，以“宜秀”为区名，含“宜城秀美”之意。"
        },
        {
            "type": "text",
            "text": "【附加】\r\n       今新安庆城之驻地古代时叫宜城渡。其地的登云坡原来的名字叫盛唐山，山下临江为盛唐湾古渡口。相传东晋诗人、堪舆风水家郭璞曾经登盛唐山观望长江，有“此地宜城”语，故安庆城别名“宜城”。\n\r\n【沿革】\r\n       1952年安庆市升为省辖市后进行区治裁并，将集贤区改为城中区。1955年3月撤销城中区，在其所属4乡及从怀宁县划入的十里铺、集贤、肖坑、谷桥、北安、竹园、五里7乡基础上成立安庆市郊区。\n\r\n       1957年10月，将东流县（今属东至县）大渡口镇及王墩乡的联发、群众、大同农业社，庆丰乡的永庆、石棋农业社，大渡口乡的镇联、正荣、新庭、合意、联合农业社划入安庆市郊区。1958年底，将怀宁县圣埠、马窝、老峰、柘山4个乡划入安庆市郊区。\n\r\n       1959年6月，撤销郊区，改设江北郊区和江南郊区。1960年，成立十里铺、广圩、大渡口3个人民公社，江北郊区区公所并入广圩公社，江南郊区区公所并入大渡口公社。\n\r\n       1962年5月恢复郊区建置，与市农林水利局合署办公，辖十里铺、白泽湖、华中路、广圩、渔业、大渡口、金鸡笼7个人民公社。1963年2月，将7个公社调整为21个公社和大渡口镇。6月，又将1957、1958年划入的乡镇（除圣埠大队）分别划回怀宁县和东至县，郊区下辖5个公社。\n\r\n       1969年初成立安庆市农业站革命委员会，行使郊区政府职能。1970年9月农业站革委会改称郊区革命委员会。1979年底，怀宁县的新洲、长风、老峰、白泽湖4个公社以及总铺公社的东风、向阳、砂桥3个大队，桐城县的杨桥、花山、大枫3个公社和罗塘公社的将军、联兴、合兴、枞南4个大队，以及破罡湖、石塘湖水面划归安庆市郊区。\n\r\n       1981年，东方红蔬菜公社与市蔬菜公司合并组建安庆市蔬菜联合总公司，并成立龙狮桥办事处承担原公社行政职能。1988年安庆市区划调整前，郊区区委与安庆市农委合署办公，郊区农林局、水产局、水利局、社队企业局对外分别加挂安庆市农林局、水产局、水利局、社队企业局衔牌。\n\r\n       2005年5月13日，安庆区划调整，撤销郊区，将原郊区的龙狮桥乡、长风乡、新洲乡和老峰镇划归迎江区，原郊区的十里铺乡（除眉山、象山、苏岗、砂桥、罗冲5个村）划归大观区，同时从怀宁县划入大龙山镇、五横乡，从桐城市划入罗岭镇，并设立大桥、菱北2个街道办事处，成立宜秀区。"
        }
    ]
}