{
    "title": "淮南市田家庵区",
    "category": [
        {
            "id": "7",
            "category": "中国地名"
        },
        {
            "id": "23",
            "category": "安徽省"
        },
        {
            "id": "1540",
            "category": "淮南市"
        }
    ],
    "detail": "[日期：2014-11-02]   来源：www.Youlai19.cn  作者：【由来网】   阅读：341次",
    "content": [
        {
            "type": "text",
            "text": "【由来】\r\n       1949年11月设田家庵市，1950年9月改为田家庵镇。1953年5月置田家庵区。田家庵之名始于清光绪年间，据传，有一田姓夫妻曾在轮船码头搭一草庵卖茶、摆渡谋生，人们便称此码头为田家庵。"
        },
        {
            "type": "text",
            "text": "【沿革】\r\n       田家庵原为淮河渡口，大通、九龙岗煤矿建成投产后，煤炭由此装船外运，成为煤港。淮南铁路通车后，发展成淮南煤矿中心集镇。1949年11月设田家庵市，1950年9月改为田家庵镇。1953年5月置田家庵区。"
        },
        {
            "type": "text",
            "text": "       2004年5月29日，将长丰县的史院乡、三和乡、曹庵镇划归淮南市田家庵区管辖。"
        },
        {
            "type": "text",
            "text": "       [参看“凤台县”词条]"
        }
    ]
}