{
    "title": "林周县所辖乡镇名称的由来",
    "category": [
        {
            "id": "7",
            "category": "中国地名"
        },
        {
            "id": "43",
            "category": "西藏自治区"
        },
        {
            "id": "233",
            "category": "拉萨市"
        },
        {
            "id": "240",
            "category": "林周县"
        }
    ],
    "detail": "[日期：2014-02-20]   来源：www.Youlai19.cn  作者：【由来网】   阅读：435次",
    "content": [
        {
            "type": "text",
            "text": "       甘丹曲果乡：“甘丹曲果”系藏语译音，意为“喜足法轮”。1960年置甘丹曲果乡，1970年改公社，1984年复置乡。"
        },
        {
            "type": "text",
            "text": "       春堆乡：“春堆”系藏语译音，意为“集市”。1960年置春堆乡，1970年改公社，1984年复置乡，1987年卡东、洛巴2乡并入。"
        },
        {
            "type": "text",
            "text": "       松昌乡：“松昌”系藏语译音，意为“分开”。1960年置松盘乡，1970年改公社，1984年复置乡，1987年岗巴、白定2乡并入，改称松昌乡。"
        },
        {
            "type": "text",
            "text": "       强嘎乡：“强嘎”系藏语译音，意为“北面”。1960年置强嘎乡，1970年改公社，1984年复置乡，1987年果际乡并入。"
        },
        {
            "type": "text",
            "text": "       改布乡：“改布”系藏语译音，意为“岸边”。1960年置克布乡，1970年改公社，1984年复置乡，1987年克布、白朗2乡合并为改布乡。"
        },
        {
            "type": "text",
            "text": "       切玛乡：“切玛”系藏语译音，意为“沙土地”。1962年置切玛乡，1970年改公社，1984年复置乡。"
        },
        {
            "type": "text",
            "text": "       班觉林乡：“班觉林”系藏语译音，意为“富饶”。1960年置班觉林乡，1970年改公社，1984年复置乡。"
        },
        {
            "type": "text",
            "text": "       朱加乡：“朱加”系藏语译音，意为“百个得道者或六百条龙”。1960年置朱加乡，1970年改公社，1984年复置乡，1989年从澎波农场划归林周县。"
        },
        {
            "type": "text",
            "text": "       江热夏乡：“江热夏”系藏语译音，意为“东柳园”。1960年置江热夏乡，1970年改公社，1984年复置乡，1989年从澎波农场划归林周县。"
        },
        {
            "type": "text",
            "text": "       卡孜乡：“卡孜”系藏语译音，意为“顶堡庄园”。1960年置卡孜乡，1970年改公社，1984年复置乡。"
        },
        {
            "type": "text",
            "text": "       牛玛乡：“牛玛”系藏语译音，意为“园根”。1960年置牛玛乡，1970年改公社，1984年复置乡。"
        },
        {
            "type": "text",
            "text": "       旁多乡：“旁多”系藏语译音，意为“山麓”。1960年置旁多乡，1970年改公社，1984年复置乡。"
        },
        {
            "type": "text",
            "text": "       塘果乡：“塘果”系藏语译音，意为“平坝”。1960年置旁多乡，1970年改公社，1984年复置乡，1987年雄堆乡、恰扎乡并入。"
        },
        {
            "type": "text",
            "text": "       阿朗乡：“阿朗”系藏语译音，意为“动物吼叫声”。1960年置阿朗乡，1970年改公社，1984年复置乡。"
        },
        {
            "type": "text",
            "text": "       拉康乡：“拉康”系藏语译音，意为“凸岗”。1960年置拉康乡，1970年改公社，1984年复置乡。"
        },
        {
            "type": "text",
            "text": "       藏雄乡：“藏雄”系藏语译音，意为“河流”。1960年置藏雄乡，1970年改公社，1984年复置乡。"
        },
        {
            "type": "text",
            "text": "       乌鲁隆乡：“乌鲁隆”系藏语译音，意为“风声”。1960年置乌鲁隆乡，1970年改公社，1984年复置乡。"
        },
        {
            "type": "text",
            "text": "       江多乡：“江多”系藏语译音，意为“抡劫口”。1960年置江多乡，1970年改公社，1984年复置乡。"
        },
        {
            "type": "text",
            "text": "       达龙乡：“达龙”系藏语译音，意为“虎”。1960年置达隆乡，1970年改公社，1984年复置乡。"
        }
    ]
}