{
    "title": "琼结县",
    "category": [
        {
            "id": "7",
            "category": "中国地名"
        },
        {
            "id": "43",
            "category": "西藏自治区"
        },
        {
            "id": "235",
            "category": "山南地区"
        },
        {
            "id": "262",
            "category": "琼结县"
        }
    ],
    "detail": "[日期：2014-02-20]   来源：www.Youlai19.cn  作者：【由来网】   阅读：346次",
    "content": [
        {
            "type": "text",
            "text": "【由来】\r\n       关于琼结宗名的来历有多种解释：一种解释认为“琼”是地名，“结”是繁荣兴旺的意思，也就是繁荣兴旺的“琼”这个地方；再一种解释含“跃狮”之意，因为原宗政府所在地“青瓦达孜宫堡”形状犹如狮子腾空雄踞山上。一说“琼”与“结”系两个部落名，合而为一作为地名。"
        },
        {
            "type": "text",
            "text": "       地名之源虽无定，但初始来自吐蕃青哇达孜宫之“青”则无疑。“琼”当是“青”之转音，故有“房角翘起多层”之意，以形容宫室之状，遂有此名。"
        },
        {
            "type": "text",
            "text": "【沿革】\r\n       琼结在历史上曾有琼巴、琼瓦、琼龙、琼域、青哇青域、匹播、跋布川、勃令驿等名称。在远古时代琼结一带就有人类活动。第一代藏王聂赤赞普时，雅砻、琼结一带称“悉补野吐蕃”，也称“蕃”或“蕃域”，是西藏最早的名称并延续下来。第八代藏王止贡赞普辞世后被葬在青域，建起第一座藏王墓。从第九代赞普止贡赞普之子布德贡坚赞普到第十五代赞普伊肖勒时期，先后在琼结青瓦山上修建了达孜、桂孜、杨孜、赤孜、孜母琼结、地则丽都等6座王宫，这就是著名的青瓦达孜宫。到朗日伦赞时（六世纪末），在琼结建立了匹播城，这是西藏最早的城堡。"
        },
        {
            "type": "text",
            "text": "       七世纪松赞干布继位，先后降服了苏毗、羊同等地，建立了统一的吐蕃王朝，把辖区分为5茹、18区、61东岱。“茹”相当于现在的地区，“东岱”是当时的千户所，琼结属于约茹青哇青域区的青隆千户所。当时茹设茹本、东岱设东岱本官职，实行区域统治。朗达玛灭佛后，其子松占据约茹。此后西藏处于分裂状态。琼结由几家大氏族分管。"
        },
        {
            "type": "text",
            "text": "       元至元五年（1268年），元朝派员同萨迦地方政权一起在西藏调查户口，并在乌思藏（即今天的西藏）设立了13个万户府。每个万户府设有万户长。唐布齐万户就是其中的一个（府址在今琼结县的唐布其乡一带）。帕莫竹巴万户府的万户长绛曲坚赞，于14世纪中叶建立了帕竹地方政权，他极力推行宗溪制度，并首批设置了13个大宗，63个溪卡，琼结即在此时期建宗，全称为琼结达孜宗。琼结达孜宗的宗址设在琼布诺布日山上，海拔3800米。西藏噶厦地方政府时期，对行政区划进行了调整，全西藏共设7个基巧，120个宗，穷结为一大宗，属于山南基巧管辖。"
        },
        {
            "type": "text",
            "text": "       1951年后，琼结宗为江孜分工委工作范围。1957年，西藏自治区筹备委员会第一次会议，《关于西藏地区行政区划的调整方案》决定，琼结宗改为琼结县，辖区不变，由山南分工委领辖。1959年后，琼结县址迁到青瓦达孜山下的琼结乡。1960年山南专区成立，琼结县即由山南专区领辖。1970年，山南专区改为山南地区，琼结县仍由山南地区领辖至今。1959年后琼结县的“琼”字曾使用“穷”字，1986年4月经国务院正式批准将“穷”改为“琼”。"
        }
    ]
}